{"events": [{"name": "cmd_run", "params": {"path_args": ["run"]}, "timestamp": 1773355174}, {"name": "cmd_run", "params": {"path_args": ["run"]}, "timestamp": 1773355074}, {"name": "cmd_run", "params": {"path_args": ["run"]}, "timestamp": 1773354666}, {"name": "cmd_run", "params": {"path_args": ["run"]}, "timestamp": 1773354645}, {"name": "cmd_run", "params": {"path_args": ["run"]}, "timestamp": 1773354415}, {"name": "cmd_run", "params": {"path_args": ["run"]}, "timestamp": 1773354249}, {"name": "cmd_run", "params": {"path_args": ["run"]}, "timestamp": 1773354220}, {"name": "cmd_run", "params": {"path_args": ["run"]}, "timestamp": 1773354155}, {"name": "cmd_run", "params": {"path_args": ["run"]}, "timestamp": 1773354127}, {"name": "platform_run", "params": {"platform": "espressif32@6.12.0", "framework": ["arduino"], "board": "esp32doit-devkit-v1", "upload_protocol": "esptool", "debug_tool": "esp-prog", "pid": "c58bdaaa92c0366c3bf3ab818d08f77e309046f4", "platform_name": "espressif32", "platform_version": "6.12.0"}, "timestamp": 1773354127}, {"name": "platform_run", "params": {"platform": "espressif32@6.12.0", "framework": ["arduino"], "board": "esp32doit-devkit-v1", "upload_protocol": "esptool", "debug_tool": "esp-prog", "pid": "c58bdaaa92c0366c3bf3ab818d08f77e309046f4", "platform_name": "espressif32", "platform_version": "6.12.0"}, "timestamp": 1773354155}, {"name": "platform_run", "params": {"platform": "espressif32@6.12.0", "framework": ["arduino"], "board": "esp32doit-devkit-v1", "upload_protocol": "esptool", "debug_tool": "esp-prog", "pid": "c58bdaaa92c0366c3bf3ab818d08f77e309046f4", "platform_name": "espressif32", "platform_version": "6.12.0"}, "timestamp": 1773354220}, {"name": "platform_run", "params": {"platform": "espressif32@6.12.0", "framework": ["arduino"], "board": "esp32doit-devkit-v1", "upload_protocol": "esptool", "debug_tool": "esp-prog", "pid": "c58bdaaa92c0366c3bf3ab818d08f77e309046f4", "platform_name": "espressif32", "platform_version": "6.12.0"}, "timestamp": 1773354249}, {"name": "platform_run", "params": {"platform": "espressif32@6.12.0", "framework": ["arduino"], "board": "esp32doit-devkit-v1", "upload_protocol": "esptool", "debug_tool": "esp-prog", "pid": "c58bdaaa92c0366c3bf3ab818d08f77e309046f4", "platform_name": "espressif32", "platform_version": "6.12.0"}, "timestamp": 1773354415}, {"name": "platform_run", "params": {"platform": "espressif32@6.12.0", "framework": ["arduino"], "board": "esp32doit-devkit-v1", "upload_protocol": "esptool", "debug_tool": "esp-prog", "pid": "c58bdaaa92c0366c3bf3ab818d08f77e309046f4", "platform_name": "espressif32", "platform_version": "6.12.0"}, "timestamp": 1773354645}, {"name": "platform_run", "params": {"platform": "espressif32@6.12.0", "framework": ["arduino"], "board": "esp32doit-devkit-v1", "upload_protocol": "esptool", "debug_tool": "esp-prog", "pid": "c58bdaaa92c0366c3bf3ab818d08f77e309046f4", "platform_name": "espressif32", "platform_version": "6.12.0"}, "timestamp": 1773354666}, {"name": "platform_run", "params": {"platform": "espressif32@6.12.0", "framework": ["arduino"], "board": "esp32doit-devkit-v1", "upload_protocol": "esptool", "debug_tool": "esp-prog", "pid": "3451f031647e39be55fb2ea474e79637e5c65483", "platform_name": "espressif32", "platform_version": "6.12.0"}, "timestamp": 1773355174}]}